devseed/__init__.py
devseed/config.py
devseed/control.py
devseed/db.py
devseed/errors.py
devseed/main.py
devseed/transformers.py
devseed/types.py
devseed-0.1.6.dist-info/entry_points.txt
devseed-0.1.6.dist-info/WHEEL
devseed-0.1.6.dist-info/METADATA
devseed-0.1.6.dist-info/RECORD
