Metadata-Version: 2.1
Name: devseed
Version: 0.1.6
Summary: Tool to seed database using YAML files
Author: Edvard Majakari
Author-email: edvard@majakari.net
Requires-Python: >=3.10,<4.0
Classifier: Programming Language :: Python :: 3
Classifier: Programming Language :: Python :: 3.10
Requires-Dist: PyPika (>=0.48.8,<0.49.0)
Requires-Dist: PyYAML (>=6.0,<7.0)
Requires-Dist: environs (>=9.5.0,<10.0.0)
Requires-Dist: funcy (>=1.17,<2.0)
Requires-Dist: loguru (>=0.6.0,<0.7.0)
Requires-Dist: orjson (>=3.6.7,<4.0.0)
Requires-Dist: pendulum (>=2.1.2,<3.0.0)
Requires-Dist: pg8000 (>=1.24.1,<2.0.0)
Requires-Dist: rich (>=11.2.0,<12.0.0)
Requires-Dist: typer[all] (>=0.4.0,<0.5.0)
